README.md
setup.py
ntier_aiohttp/__init__.py
ntier_aiohttp/connect.py
ntier_aiohttp/deserialize.py
ntier_aiohttp/py.typed
ntier_aiohttp.egg-info/PKG-INFO
ntier_aiohttp.egg-info/SOURCES.txt
ntier_aiohttp.egg-info/dependency_links.txt
ntier_aiohttp.egg-info/not-zip-safe
ntier_aiohttp.egg-info/requires.txt
ntier_aiohttp.egg-info/top_level.txt