Metadata-Version: 2.1
Name: ntier-aiohttp
Version: 1.0.1
Summary: Adapt N-Tier to aiohttp
Home-page: https://gitlab.com/tcucco/ntier-aiohttp
Author: Trey Cucco
Author-email: fcucco@gmail.com
License: MIT
Download-URL: https://gitlab.com/tcucco/ntier-aiohttp/-/archive/master/ntier-aiohttp-master.tar.gz
Platform: any
Classifier: Development Status :: 4 - Beta
Classifier: Intended Audience :: Developers
Classifier: License :: OSI Approved :: MIT License
Classifier: Natural Language :: English
Classifier: Operating System :: OS Independent
Classifier: Programming Language :: Python :: 3.7
